fiknight/__init__.py
fiknight/fsm/__init__.py
fiknight/fsm/core.py
fiknight/fsm/errors.py
fiknight/fsm/common/__init__.py
fiknight/fsm/common/events.py
fiknight/fsm/export/__init__.py
fiknight/fsm/export/networkx.py
fiknight/fsm/tests/__init__.py
fiknight-0.1.0.dist-info/COPYING.md
fiknight-0.1.0.dist-info/METADATA
fiknight-0.1.0.dist-info/WHEEL
fiknight-0.1.0.dist-info/entry_points.txt
fiknight-0.1.0.dist-info/top_level.txt
fiknight-0.1.0.dist-info/RECORD
