Metadata-Version: 2.1
Name: fiknight
Version: 0.1.0
Summary: A simple package implementing a finite state machine.
Home-page: https://gitlab.com/Trijeet/fiknight
Author: Trijeet Sethi
Author-email: trijeets@gmail.com
License: UNKNOWN
Platform: UNKNOWN
Classifier: Programming Language :: Python :: 3
Classifier: Operating System :: OS Independent
Classifier: Development Status :: 2 - Pre-Alpha
Classifier: Natural Language :: English
Requires-Python: >=3.6
